{
  "attributes": {
    "twx-widget": "",
    "widget-id": "view-1",
    "widget-name": "view-1",
    "is-widget-container": "true",
    "viewtype": "ar"
  },
  "children": [
    {
      "name": "twx-container-content",
      "children": [
        {
          "attributes": {
            "twx-widget": "",
            "widget-id": "3DContainer-1",
            "widget-name": "3D Container",
            "is-widget-container": "true",
            "dropshadow": "true"
          },
          "name": "twx-dt-view",
          "children": [
            {
              "name": "twx-container-content",
              "children": [
                {
                  "attributes": {
                    "twx-widget": "",
                    "widget-id": "model-7",
                    "widget-name": "Counter2",
                    "is-widget-container": "true",
                    "src": "Uploaded/Reception 01_Med.pvz",
                    "scale": "0.3000",
                    "x": "-12.2719",
                    "y": "-4.8260",
                    "z": "-13.8499",
                    "rx": "-0.02",
                    "ry": "2.42",
                    "rz": "-0.50"
                  },
                  "name": "twx-dt-model",
                  "children": [
                    {
                      "name": "twx-container-content"
                    }
                  ]
                },
                {
                  "attributes": {
                    "twx-widget": "",
                    "widget-id": "model-4",
                    "widget-name": "Counter1",
                    "is-widget-container": "true",
                    "src": "Uploaded/Reception 01_Med.pvz",
                    "scale": "0.3000",
                    "x": "-17.5336",
                    "y": "-2.7689",
                    "z": "46.9532",
                    "rx": "-2.00",
                    "ry": "6.63",
                    "rz": "-0.00"
                  },
                  "name": "twx-dt-model",
                  "children": [
                    {
                      "name": "twx-container-content"
                    }
                  ]
                },
                {
                  "attributes": {
                    "twx-widget": "",
                    "widget-id": "model-6",
                    "widget-name": "Counter3",
                    "is-widget-container": "true",
                    "src": "Uploaded/Reception 01_Med.pvz",
                    "scale": "0.3000",
                    "x": "34.9183",
                    "y": "-4.1236",
                    "z": "-31.6246",
                    "rx": "0.10",
                    "ry": "6.63",
                    "rz": "0.00"
                  },
                  "name": "twx-dt-model",
                  "children": [
                    {
                      "name": "twx-container-content"
                    }
                  ]
                },
                {
                  "attributes": {
                    "twx-widget": "",
                    "widget-id": "spatialTarget-1",
                    "widget-name": "spatialTarget-1",
                    "x": "7.0627",
                    "y": "0.0000",
                    "z": "34.2518",
                    "rx": "-90.00",
                    "ry": "0.00",
                    "rz": "0.00",
                    "enablescalegesture": "true"
                  },
                  "name": "twx-dt-target-spatial"
                },
                {
                  "attributes": {
                    "twx-widget": "",
                    "widget-id": "3DLabel-1",
                    "state-format-value": "text",
                    "widget-name": "3DLabel-1",
                    "text": "Your Airline Counter",
                    "height": "15",
                    "width": "30",
                    "scale": "1.0000",
                    "x": "-13.1417",
                    "y": "39.1310",
                    "z": "-18.9104",
                    "rx": "-18.59",
                    "ry": "30.42",
                    "rz": "3.27"
                  },
                  "name": "twx-dt-label"
                },
                {
                  "attributes": {
                    "twx-widget": "",
                    "widget-id": "model-9",
                    "widget-name": "model-9",
                    "is-widget-container": "true",
                    "src": "Uploaded/15797 Pointer_v1_new.pvz",
                    "scale": "0.8000",
                    "x": "36.4692",
                    "y": "-9.9735",
                    "z": "59.3420",
                    "rx": "117.32",
                    "ry": "-23.19",
                    "rz": "92.78"
                  },
                  "name": "twx-dt-model",
                  "children": [
                    {
                      "name": "twx-container-content"
                    }
                  ]
                },
                {
                  "attributes": {
                    "twx-widget": "",
                    "widget-id": "model-1",
                    "widget-name": "model-1",
                    "is-widget-container": "true",
                    "src": "Uploaded/15797 Pointer_v1_new.pvz",
                    "scale": "0.8000",
                    "x": "-1.9926",
                    "y": "12.6454",
                    "z": "-6.1524",
                    "rx": "130.48",
                    "ry": "-17.80",
                    "rz": "100.10"
                  },
                  "name": "twx-dt-model",
                  "children": [
                    {
                      "name": "twx-container-content"
                    }
                  ]
                },
                {
                  "attributes": {
                    "twx-widget": "",
                    "widget-id": "model-2",
                    "widget-name": "model-2",
                    "is-widget-container": "true",
                    "src": "Uploaded/15797 Pointer_v1_new.pvz",
                    "scale": "0.8000",
                    "x": "27.7865",
                    "y": "6.3345",
                    "z": "29.7744",
                    "rx": "129.51",
                    "ry": "-20.16",
                    "rz": "103.07"
                  },
                  "name": "twx-dt-model",
                  "children": [
                    {
                      "name": "twx-container-content"
                    }
                  ]
                },
                {
                  "attributes": {
                    "twx-widget": "",
                    "widget-id": "model-3",
                    "widget-name": "model-3",
                    "is-widget-container": "true",
                    "src": "Uploaded/rp_mei_posed_001_100k_Med.pvz",
                    "scale": "0.4000",
                    "x": "-44.9837",
                    "y": "-0.1611",
                    "z": "-40.8424",
                    "rx": "0.00",
                    "ry": "48.66",
                    "rz": "0.00"
                  },
                  "name": "twx-dt-model",
                  "children": [
                    {
                      "name": "twx-container-content"
                    }
                  ]
                }
              ]
            }
          ]
        },
        {
          "attributes": {
            "twx-widget": "",
            "widget-id": "2DOverlay-1",
            "widget-name": "2D Overlay",
            "is-widget-container": "true"
          },
          "name": "twx-overlay",
          "children": [
            {
              "name": "twx-container-content",
              "children": [
                {
                  "attributes": {
                    "twx-widget": "",
                    "widget-id": "2DOverlayBody-1",
                    "widget-name": "2D Body",
                    "is-widget-container": "true"
                  },
                  "name": "twx-overlay-body",
                  "children": [
                    {
                      "name": "twx-container-content",
                      "children": [
                        {
                          "attributes": {
                            "twx-widget": "",
                            "widget-id": "panel-2",
                            "widget-name": "Left Panel",
                            "is-widget-container": "true",
                            "position": "left"
                          },
                          "name": "twx-overlay-container",
                          "children": [
                            {
                              "name": "twx-container-content"
                            }
                          ]
                        },
                        {
                          "attributes": {
                            "twx-widget": "",
                            "widget-id": "panel-3",
                            "widget-name": "Center Panel",
                            "is-widget-container": "true",
                            "position": "center"
                          },
                          "name": "twx-overlay-container",
                          "children": [
                            {
                              "name": "twx-container-content"
                            }
                          ]
                        },
                        {
                          "attributes": {
                            "twx-widget": "",
                            "widget-id": "panel-4",
                            "widget-name": "Right Panel",
                            "is-widget-container": "true",
                            "position": "right"
                          },
                          "name": "twx-overlay-container",
                          "children": [
                            {
                              "name": "twx-container-content"
                            }
                          ]
                        }
                      ]
                    }
                  ]
                },
                {
                  "attributes": {
                    "twx-widget": "",
                    "widget-id": "panel-5",
                    "widget-name": "Bottom Panel",
                    "is-widget-container": "true",
                    "position": "bottom"
                  },
                  "name": "twx-overlay-container",
                  "children": [
                    {
                      "name": "twx-container-content"
                    }
                  ]
                }
              ]
            }
          ]
        }
      ]
    },
    {
      "name": "twx-fragment-parameters"
    },
    {
      "name": "twx-view-data"
    }
  ],
  "name": "twx-view"
}
